py_csv_xls/__init__.py
py_csv_xls/csvsniffer.py
py_csv_xls/excelworker.py
py_csv_xls/exception.py
py_csv_xls-0.0.6.dist-info/LICENSE
py_csv_xls-0.0.6.dist-info/METADATA
py_csv_xls-0.0.6.dist-info/WHEEL
py_csv_xls-0.0.6.dist-info/top_level.txt
py_csv_xls-0.0.6.dist-info/RECORD
