Metadata-Version: 2.1
Name: py-csv-xls
Version: 0.0.6
Summary: Converter from csv format to xls
Home-page: https://github.com/pog7x/py-csv-xls
Author: pog7x
Author-email: poluningm@gmail.com
License: MIT
Keywords: python csv xls excel date
Classifier: License :: OSI Approved :: MIT License
Classifier: Operating System :: OS Independent
Classifier: Programming Language :: Python
Classifier: Programming Language :: Python :: 3.7
Classifier: Programming Language :: Python :: 3.8
Classifier: Programming Language :: Python :: 3.9
Classifier: Programming Language :: Python :: 3.10
Classifier: Programming Language :: Python :: 3.11
Classifier: Programming Language :: Python :: Implementation :: CPython
Classifier: Programming Language :: Python :: Implementation :: PyPy
Requires-Python: >=3.7
License-File: LICENSE
Requires-Dist: openpyxl (==3.0.10)
